LICENSE.txt
MANIFEST.in
README.rst
setup.py
bin/redhawk
editors/vim/doc/redhawk.txt
editors/vim/plugin/redhawk.vim
redhawk/__init__.py
redhawk.egg-info/PKG-INFO
redhawk.egg-info/SOURCES.txt
redhawk.egg-info/dependency_links.txt
redhawk.egg-info/requires.txt
redhawk.egg-info/top_level.txt
redhawk/c/__init__.py
redhawk/c/c_parser.py
redhawk/c/c_tree_converter.py
redhawk/c/fake_libc_include/_ansi.h
redhawk/c/fake_libc_include/_fake_defines.h
redhawk/c/fake_libc_include/_fake_typedefs.h
redhawk/c/fake_libc_include/_syslist.h
redhawk/c/fake_libc_include/alloca.h
redhawk/c/fake_libc_include/ar.h
redhawk/c/fake_libc_include/argz.h
redhawk/c/fake_libc_include/assert.h
redhawk/c/fake_libc_include/ctype.h
redhawk/c/fake_libc_include/dirent.h
redhawk/c/fake_libc_include/envz.h
redhawk/c/fake_libc_include/errno.h
redhawk/c/fake_libc_include/fastmath.h
redhawk/c/fake_libc_include/fcntl.h
redhawk/c/fake_libc_include/getopt.h
redhawk/c/fake_libc_include/grp.h
redhawk/c/fake_libc_include/iconv.h
redhawk/c/fake_libc_include/ieeefp.h
redhawk/c/fake_libc_include/inttypes.h
redhawk/c/fake_libc_include/langinfo.h
redhawk/c/fake_libc_include/libgen.h
redhawk/c/fake_libc_include/limits.h
redhawk/c/fake_libc_include/locale.h
redhawk/c/fake_libc_include/malloc.h
redhawk/c/fake_libc_include/math.h
redhawk/c/fake_libc_include/newlib.h
redhawk/c/fake_libc_include/paths.h
redhawk/c/fake_libc_include/process.h
redhawk/c/fake_libc_include/pthread.h
redhawk/c/fake_libc_include/pwd.h
redhawk/c/fake_libc_include/reent.h
redhawk/c/fake_libc_include/regdef.h
redhawk/c/fake_libc_include/sched.h
redhawk/c/fake_libc_include/search.h
redhawk/c/fake_libc_include/setjmp.h
redhawk/c/fake_libc_include/signal.h
redhawk/c/fake_libc_include/stdarg.h
redhawk/c/fake_libc_include/stddef.h
redhawk/c/fake_libc_include/stdint.h
redhawk/c/fake_libc_include/stdio.h
redhawk/c/fake_libc_include/stdlib.h
redhawk/c/fake_libc_include/string.h
redhawk/c/fake_libc_include/tar.h
redhawk/c/fake_libc_include/termios.h
redhawk/c/fake_libc_include/time.h
redhawk/c/fake_libc_include/unctrl.h
redhawk/c/fake_libc_include/unistd.h
redhawk/c/fake_libc_include/utime.h
