Metadata-Version: 1.1
Name: redhawk
Version: 1.2.2
Summary: An AST based navigation system.
Home-page: http://pypi.python.org/pypi/redhawk/
Author: Pranesh Srinivasan
Author-email: spranesh@gmail.com
License: The BSD 2-Clause License
Platform: UNKNOWN
Classifier: Development Status :: 3 - Alpha
Classifier: Environment :: Console
Classifier: Environment :: Plugins
Classifier: Intended Audience :: Developers
Classifier: License :: OSI Approved :: BSD License
Classifier: Operating System :: POSIX :: Linux
Classifier: Programming Language :: C
Classifier: Programming Language :: Python :: 2.6
Classifier: Programming Language :: Python :: 2.7
Classifier: Topic :: Software Development
Classifier: Topic :: Utilities
